homophone/__init__.py
homophone/__main__.py
homophone/artist.py
homophone/auth.py
homophone/formatter.py
homophone/service.py
homophone-1.1.3.dist-info/METADATA
homophone-1.1.3.dist-info/RECORD
homophone-1.1.3.dist-info/WHEEL
homophone-1.1.3.dist-info/entry_points.txt
homophone-1.1.3.dist-info/top_level.txt
